{"BaseModel.d1b73b1f-b86f-4d86-9ab7-6a7ee3ea0429": {"id": "d1b73b1f-b86f-4d86-9ab7-6a7ee3ea0429", "created_at": "2023-12-09T12:53:10.431721", "updated_at": "2023-12-09T12:53:10.431768", "name": "My_First_Model", "my_number": 89, "__class__": "BaseModel"}, "BaseModel.28848456-6641-49b2-b49f-c3956f2ad05c": {"id": "28848456-6641-49b2-b49f-c3956f2ad05c", "created_at": "2023-12-09T12:53:32.639613", "updated_at": "2023-12-09T12:53:32.639651", "name": "My_First_Model", "my_number": 89, "__class__": "BaseModel"}}